mat_view-0.1b2.data/scripts/MAT-ExportResults.py
mat_view-0.1b2.data/scripts/MAT-MoveResults.py
mat_view-0.1b2.data/scripts/MAT-PrintResults.py
mat_view-0.1b2.data/scripts/MAT-Summary.py
mat_view-0.1b2.data/scripts/MAT-Web.py
matview/LICENSE
matview/README.md
matview/__init__.py
matview/assets/css/appstyle.css
matview/assets/data/experimental_history-timeseries.csv
matview/assets/data/experimental_history-ultra.csv
matview/assets/data/experimental_history.csv
matview/assets/img/favicon.ico
matview/assets/img/mat.svg
matview/graph/__init__.py
matview/graph/helper.py
matview/graph/movelet/heatmap.py
matview/graph/movelet/markov.py
matview/graph/movelet/markovtree.py
matview/graph/movelet/moveletdt.py
matview/graph/movelet/qstree.py
matview/graph/movelet/sankey.py
matview/plot/__init__.py
matview/plot/bar.py
matview/plot/bar_mean.py
matview/plot/box.py
matview/plot/critical_difference.py
matview/plot/line_rank.py
matview/plot/swarm.py
matview/scripting/__init__.py
matview/scripting/generator.py
matview/scripting/result.py
matview/scripting/component/__init__.py
matview/scripting/component/_base.py
matview/scripting/component/hiper.py
matview/scripting/component/marc.py
matview/scripting/component/master.py
matview/scripting/component/mat.py
matview/scripting/component/pois.py
matview/scripting/component/raw.py
matview/scripting/component/super.py
matview/scripting/component/ultra.py
matview/util/__init__.py
matview/util/format.py
matview/util/stats.py
matview/web/__init__.py
matview/web/app.py
matview/web/app_base.py
matview/web/config.py
matview/web/definitions.py
matview/web/dataset/__init__.py
matview/web/dataset/datasets.md
matview/web/dataset/main.py
matview/web/method/__init__.py
matview/web/method/classification.md
matview/web/method/clustering.md
matview/web/method/main.py
matview/web/method/similarity.md
matview/web/method/summarization.md
matview/web/method/classification/BITULER.md
matview/web/method/classification/DeepeST.md
mat_view-0.1b2.dist-info/LICENSE
mat_view-0.1b2.dist-info/METADATA
mat_view-0.1b2.dist-info/WHEEL
mat_view-0.1b2.dist-info/top_level.txt
mat_view-0.1b2.dist-info/RECORD
