Metadata-Version: 2.1
Name: mat-view
Version: 0.1b2
Summary: MAT-view: Visualization Tools for Multiple Aspect Trajectory Data Mining
Home-page: https://github.com/ttportela/movelets
Author: Tarlis Tortelli Portela
Author-email: Tarlis Tortelli Portela <tarlis@tarlis.com.br>
Maintainer-email: Tarlis Tortelli Portela <tarlis@tarlis.com.br>
License: GPL Version 3 or superior (see LICENSE file)
Project-URL: Homepage, https://github.com/mat-analysis/mat-view
Project-URL: Repository, https://github.com/mat-analysis/mat-view
Project-URL: Documentation, https://github.com/mat-analysis/mat-view/blob/main/README.md
Project-URL: Download, https://pypi.org/project/mat-view/#files
Project-URL: Bug Tracker, https://github.com/mat-analysis/mat-view/issues
Keywords: data-science,machine-learning,data-mining,trajectory,multiple-trajectory,trajectory-classification,movelet,movelet-visualization
Classifier: Intended Audience :: Science/Research
Classifier: Intended Audience :: Developers
Classifier: License :: OSI Approved :: GNU General Public License v3 or later (GPLv3+)
Classifier: Programming Language :: Python
Classifier: Topic :: Software Development
Classifier: Topic :: Scientific/Engineering
Classifier: Topic :: Scientific/Engineering :: Artificial Intelligence
Classifier: Topic :: Scientific/Engineering :: Information Analysis
Classifier: Topic :: Scientific/Engineering :: Visualization
Classifier: Operating System :: OS Independent
Classifier: Operating System :: Microsoft :: Windows
Classifier: Operating System :: POSIX
Classifier: Operating System :: Unix
Classifier: Operating System :: MacOS
Classifier: Programming Language :: Python :: 3.10
Requires-Python: <3.10
License-File: LICENSE
Requires-Dist: glob2 ==0.7
Requires-Dist: numpy
Requires-Dist: pandas ==1.3.4
Requires-Dist: mat-data
Requires-Dist: mat-model
Provides-Extra: all_extras
Requires-Dist: geohash ; extra == 'all_extras'
Provides-Extra: binder
Requires-Dist: jupyter ; extra == 'binder'
Provides-Extra: dev
Requires-Dist: pre-commit ; extra == 'dev'
Requires-Dist: pytest ; extra == 'dev'
Requires-Dist: pytest-cov ; extra == 'dev'
Requires-Dist: pytest-xdist ; extra == 'dev'
Requires-Dist: wheel ; extra == 'dev'
Provides-Extra: dl
Provides-Extra: docs
Requires-Dist: jupyter ; extra == 'docs'
Requires-Dist: numpydoc ; extra == 'docs'
